linden/__init__.py
linden/config/__init__.py
linden/config/configuration.py
linden/core/__init__.py
linden/core/agent_runner.py
linden/core/model.py
linden/memory/__init__.py
linden/memory/agent_memory.py
linden/provider/__init__.py
linden/provider/ai_client.py
linden/provider/anthropic.py
linden/provider/groq.py
linden/provider/ollama.py
linden/provider/openai.py
linden/utils/__init__.py
linden/utils/doc_string_parser.py
linden-0.4.0.dist-info/licenses/LICENSE
linden-0.4.0.dist-info/METADATA
linden-0.4.0.dist-info/WHEEL
linden-0.4.0.dist-info/top_level.txt
linden-0.4.0.dist-info/RECORD
