Metadata-Version: 2.4
Name: linden
Version: 0.4.0
Summary: A Python framework for building AI agents with multi-provider LLM support, persistent memory, and function calling capabilities.
Author-email: Matteo Stabile <matteo.stabile2@gmail.com>
License-Expression: MIT
Project-URL: Homepage, https://github.com/matstech/linden
Project-URL: Bug Tracker, https://github.com/matstech/linden/issues
Classifier: Programming Language :: Python :: 3
Classifier: Operating System :: OS Independent
Requires-Python: >=3.10
License-File: LICENSE
Requires-Dist: docstring_parser==0.17.0
Requires-Dist: pydantic==2.11.7
Requires-Dist: Requests==2.32.5
Requires-Dist: mem0ai==0.1.116
Requires-Dist: anthropic==0.64.0
Requires-Dist: ollama==0.5.3
Requires-Dist: openai==1.101.0
Requires-Dist: groq==0.31.0
Requires-Dist: tomli
Provides-Extra: test
Requires-Dist: pytest>=8.0.0; extra == "test"
Requires-Dist: pytest-cov>=5.0.0; extra == "test"
Requires-Dist: pytest-mock>=3.12.0; extra == "test"
Requires-Dist: pytest-asyncio>=0.23.6; extra == "test"
Requires-Dist: responses>=0.25.0; extra == "test"
Provides-Extra: dev
Requires-Dist: black>=24.1.0; extra == "dev"
Requires-Dist: isort>=5.13.0; extra == "dev"
Requires-Dist: flake8>=7.0.0; extra == "dev"
Requires-Dist: mypy>=1.8.0; extra == "dev"
Provides-Extra: all
Requires-Dist: pytest>=8.0.0; extra == "all"
Requires-Dist: pytest-cov>=5.0.0; extra == "all"
Requires-Dist: pytest-mock>=3.12.0; extra == "all"
Requires-Dist: pytest-asyncio>=0.23.6; extra == "all"
Requires-Dist: responses>=0.25.0; extra == "all"
Requires-Dist: black>=24.1.0; extra == "all"
Requires-Dist: isort>=5.13.0; extra == "all"
Requires-Dist: flake8>=7.0.0; extra == "all"
Requires-Dist: mypy>=1.8.0; extra == "all"
Dynamic: license-file
